pyCoilGenData/__init__.py
pyCoilGenData/Geometry_Data/Cone_shaped_self_shielding_surface.stl
pyCoilGenData/Geometry_Data/Cone_shaped_self_shielding_surface2.stl
pyCoilGenData/Geometry_Data/Double_coaxial_open_cylinder_r1_400mm_r2_600_length_1500mm.stl
pyCoilGenData/Geometry_Data/Open_cylinder_r750mm_length_1500mm.stl
pyCoilGenData/Geometry_Data/Primary_r500mm_l1500mm_Shield_r750mm_l1750mm.stl
pyCoilGenData/Geometry_Data/bi_planer_rectangles_width_1000mm_distance_500mm.stl
pyCoilGenData/Geometry_Data/closed_cylinder_length_300mm_radius_150mm.stl
pyCoilGenData/Geometry_Data/closed_cylinder_radius10mm_length40mm.stl
pyCoilGenData/Geometry_Data/cylinder_radius500mm_length1500mm.stl
pyCoilGenData/Geometry_Data/cylinder_radius500mm_length1500mm_90deg_rotated.stl
pyCoilGenData/Geometry_Data/cylinder_radius500mm_length1500mm_holes_250mm.stl
pyCoilGenData/Geometry_Data/cylinder_radius500mm_length1500mm_regular_holes.stl
pyCoilGenData/Geometry_Data/cylinder_radius50mm_length350mm.stl
pyCoilGenData/Geometry_Data/cylinder_radius600mm_length_1500mm_regular.stl
pyCoilGenData/Geometry_Data/cylinder_radius900mm_length_1900mm_regular.stl
pyCoilGenData/Geometry_Data/dental_ccs_bionic.stl
pyCoilGenData/Geometry_Data/dental_ccs_bionic_shift_1cm_in_y.stl
pyCoilGenData/Geometry_Data/dental_extraoral_ccs.stl
pyCoilGenData/Geometry_Data/dental_extraoral_ccs2_shifted_2cm_in_y.stl
pyCoilGenData/Geometry_Data/dental_gradient_ccs.stl
pyCoilGenData/Geometry_Data/dental_gradient_ccs_single_low.stl
pyCoilGenData/Geometry_Data/dental_gradient_target_region.stl
pyCoilGenData/Geometry_Data/dental_gradient_target_region_single_low.stl
pyCoilGenData/Geometry_Data/dental_oral_target.stl
pyCoilGenData/Geometry_Data/dental_oral_target_bionic.stl
pyCoilGenData/Geometry_Data/dental_oral_target_shifted_1cm_in_y.stl
pyCoilGenData/Geometry_Data/diamond_probe_gradient_css.stl
pyCoilGenData/Geometry_Data/diamond_probe_target_surface.stl
pyCoilGenData/Geometry_Data/half_sphere_shape.stl
pycoilgen_data-0.0.4.dist-info/LICENSE.txt
pycoilgen_data-0.0.4.dist-info/WHEEL
pycoilgen_data-0.0.4.dist-info/METADATA
pycoilgen_data-0.0.4.dist-info/RECORD
